mincepy/__init__.py
mincepy/_autosave.py
mincepy/archive_factory.py
mincepy/archives.py
mincepy/base_savable.py
mincepy/builtins.py
mincepy/common_helpers.py
mincepy/comparators.py
mincepy/defaults.py
mincepy/depositors.py
mincepy/exceptions.py
mincepy/expr.py
mincepy/fields.py
mincepy/files.py
mincepy/frontend.py
mincepy/helpers.py
mincepy/historians.py
mincepy/history.py
mincepy/migrate.py
mincepy/migrations.py
mincepy/operations.py
mincepy/plugins.py
mincepy/process.py
mincepy/provides.py
mincepy/qops.py
mincepy/records.py
mincepy/refs.py
mincepy/result_types.py
mincepy/saving.py
mincepy/staging.py
mincepy/testing.py
mincepy/tracking.py
mincepy/transactions.py
mincepy/type_ids.py
mincepy/type_registry.py
mincepy/types.py
mincepy/typing.py
mincepy/utils.py
mincepy/version.py
mincepy/cli/__init__.py
mincepy/cli/dev.py
mincepy/cli/main.py
mincepy/cli/query.py
mincepy/hist/__init__.py
mincepy/hist/live_objects.py
mincepy/hist/metas.py
mincepy/hist/references.py
mincepy/hist/snapshots.py
mincepy/mongo/__init__.py
mincepy/mongo/aggregation.py
mincepy/mongo/bulk.py
mincepy/mongo/db.py
mincepy/mongo/migrate.py
mincepy/mongo/migrations.py
mincepy/mongo/mongo_archive.py
mincepy/mongo/queries.py
mincepy/mongo/references.py
mincepy/mongo/settings.py
mincepy/mongo/types.py
mincepy-0.18.0.dist-info/entry_points.txt
mincepy-0.18.0.dist-info/licenses/LICENSE.txt
mincepy-0.18.0.dist-info/WHEEL
mincepy-0.18.0.dist-info/METADATA
mincepy-0.18.0.dist-info/RECORD
