Metadata-Version: 2.4
Name: mincepy
Version: 0.18.0
Summary: mincePy: move the database to one side and let your objects take centre stage.
Keywords: database,schemaless,nosql,orm,object-store,concurrent,optimistic-locking
Author-email: Martin Uhrin <martin.uhrin.10@ucl.ac.uk>
Requires-Python: >=3.9
Classifier: Development Status :: 4 - Beta
Classifier: License :: OSI Approved :: GNU Lesser General Public License v3 or later (LGPLv3+)
Classifier: Programming Language :: Python
Classifier: Programming Language :: Python :: 3.9
Classifier: Programming Language :: Python :: 3.10
Classifier: Programming Language :: Python :: 3.11
Classifier: Programming Language :: Python :: 3.12
Classifier: Programming Language :: Python :: 3.13
License-File: LICENSE.txt
Requires-Dist: deprecation
Requires-Dist: dnspython
Requires-Dist: pymongo<5.0
Requires-Dist: litemongo
Requires-Dist: importlib-metadata<5.0
Requires-Dist: mongomock
Requires-Dist: bidict
Requires-Dist: networkx
Requires-Dist: pytray>=0.2.1
Requires-Dist: stevedore
Requires-Dist: click
Requires-Dist: tabulate
Requires-Dist: tqdm
Requires-Dist: typing-extensions
Requires-Dist: click ; extra == "cli"
Requires-Dist: tabulate ; extra == "cli"
Requires-Dist: black ; extra == "dev"
Requires-Dist: flit ; extra == "dev"
Requires-Dist: ipython ; extra == "dev"
Requires-Dist: mongomock ; extra == "dev"
Requires-Dist: pip ; extra == "dev"
Requires-Dist: pylint ; extra == "dev"
Requires-Dist: pytest>4 ; extra == "dev"
Requires-Dist: pytest-benchmark ; extra == "dev"
Requires-Dist: pytest-cov ; extra == "dev"
Requires-Dist: pre-commit ; extra == "dev"
Requires-Dist: yapf ; extra == "dev"
Requires-Dist: nbsphinx ; extra == "docs"
Requires-Dist: sphinx ; extra == "docs"
Requires-Dist: sphinx-autobuild ; extra == "docs"
Requires-Dist: mincepy-gui ; extra == "gui"
Requires-Dist: mincepy-sci ; extra == "sci"
Project-URL: Home, https://mincepy.readthedocs.io/en/latest/index.html
Project-URL: Source, https://github.com/muhrin/mincepy.git
Provides-Extra: cli
Provides-Extra: dev
Provides-Extra: docs
Provides-Extra: gui
Provides-Extra: sci
